LICENSE
fastapi_cloudauth/__init__.py
fastapi_cloudauth/auth0.py
fastapi_cloudauth/base.py
fastapi_cloudauth/cognito.py
fastapi_cloudauth/firebase.py
fastapi_cloudauth/messages.py
fastapi_cloudauth/verification.py
fastapi_cloudauth-0.4.3.dist-info/LICENSE
fastapi_cloudauth-0.4.3.dist-info/WHEEL
fastapi_cloudauth-0.4.3.dist-info/METADATA
fastapi_cloudauth-0.4.3.dist-info/RECORD
