Metadata-Version: 2.1
Name: fastapi-cloudauth
Version: 0.4.3
Summary: fastapi-cloudauth supports simple integration between FastAPI and cloud authentication services (AWS Cognito, Auth0, Firebase Authentication).
Home-page: https://github.com/tokusumi/fastapi-cloudauth
License: MIT
Keywords: FastAPI,authentication,Auth0,AWS Cognito,Firebase Authentication
Author: tokusumi
Author-email: tksmtoms@gmail.com
Requires-Python: >=3.6.2,<4.0
Classifier: Environment :: Web Environment
Classifier: License :: OSI Approved :: MIT License
Classifier: Operating System :: OS Independent
Classifier: Programming Language :: Python :: 3
Classifier: Programming Language :: Python :: 3 :: Only
Classifier: Programming Language :: Python :: 3.10
Classifier: Programming Language :: Python :: 3.6
Classifier: Programming Language :: Python :: 3.7
Classifier: Programming Language :: Python :: 3.8
Classifier: Programming Language :: Python :: 3.9
Classifier: Topic :: Security
Classifier: Typing :: Typed
Requires-Dist: fastapi (>=0.60.1,<1.0)
Requires-Dist: python-jose[cryptography] (>=3.3.0,<4.0.0)
Requires-Dist: requests (>=2.24.0,<3.0.0)
Project-URL: Repository, https://github.com/tokusumi/fastapi-cloudauth
